pybuster/__init__.py
pybuster/client.py
pybuster/logger.py
pybuster/pybuster.py
pybuster-0.2.1.dist-info/LICENSE
pybuster-0.2.1.dist-info/METADATA
pybuster-0.2.1.dist-info/WHEEL
pybuster-0.2.1.dist-info/entry_points.txt
pybuster-0.2.1.dist-info/top_level.txt
pybuster-0.2.1.dist-info/RECORD
