Metadata-Version: 2.1
Name: pybuster
Version: 0.2.1
Summary: A multithreaded brute-forcing tool for use with web URIs
Home-page: https://github.com/leokon/pybuster
Author: Leo Kontogiorgis
Author-email: leo@konto.dev
License: UNKNOWN
Platform: UNKNOWN
Requires-Dist: requests
Requires-Dist: tqdm
